testrail_interface.py
testrail_interface-0.0.3.dist-info/METADATA
testrail_interface-0.0.3.dist-info/WHEEL
testrail_interface-0.0.3.dist-info/licenses/LICENCE
testrail_interface-0.0.3.dist-info/RECORD
