Metadata-Version: 2.1
Name: testrail_interface
Version: 0.0.3
Summary: A small testrail interface package
Author-email: Petr Volkov <pvolkov20001130@gmail.com>
License-File: LICENCE
Classifier: License :: OSI Approved :: MIT License
Classifier: Operating System :: OS Independent
Classifier: Programming Language :: Python :: 3
Requires-Python: >=3.10
